NoteBookSearch/DataManager.py
NoteBookSearch/DataRead.py
NoteBookSearch/NoteBookSearch.py
NoteBookSearch/SEARCH_ENGINE.py
NoteBookSearch/__init__.py
NoteBookSearch/__version__.py
NoteSearch/NoteSearch.py
NoteSearch/Note_search.py
NoteSearch/__init__.py
NoteSearch/__version__.py
Note_Search/Note_search.py
Note_Search/__init__.py
Note_Search/__version__.py
Test/Note_Search_Tests.py
Test/Question2.py
Test/__init__.py
Test/test_jason.py
Test/testing_os_walk.py
Test/whyJsaon.py
NoteBookSearch-0.0.7.dist-info/LICENSE
NoteBookSearch-0.0.7.dist-info/METADATA
NoteBookSearch-0.0.7.dist-info/WHEEL
NoteBookSearch-0.0.7.dist-info/top_level.txt
NoteBookSearch-0.0.7.dist-info/RECORD
