Metadata-Version: 2.1
Name: NoteBookSearch
Version: 0.0.7
Summary: This is a tool to search key word in a folder.
Home-page: https://github.com/WilliamQx/Note_Search
Author: William Karon Leung
Author-email: WilliamKaronLG@outlook.com
License: MIT
Platform: UNKNOWN
Classifier: License :: OSI Approved :: MIT License
Classifier: Programming Language :: Python
Classifier: Programming Language :: Python :: 3
Classifier: Programming Language :: Python :: 3.6
Classifier: Programming Language :: Python :: Implementation :: CPython
Classifier: Programming Language :: Python :: Implementation :: PyPy
Requires-Python: >=3.6.0
License-File: LICENSE
